pymaven/__init__.py
pymaven/artifact.py
pymaven/client.py
pymaven/constants.py
pymaven/errors.py
pymaven/pom.py
pymaven/utils.py
pymaven/versioning.py
pymaven-0.2.0.dist-info/DESCRIPTION.rst
pymaven-0.2.0.dist-info/METADATA
pymaven-0.2.0.dist-info/RECORD
pymaven-0.2.0.dist-info/WHEEL
pymaven-0.2.0.dist-info/metadata.json
pymaven-0.2.0.dist-info/top_level.txt
