Metadata-Version: 2.0
Name: pymaven
Version: 0.2.0
Summary: Python access to maven
Home-page: UNKNOWN
Author: Walter Scheper
Author-email: Walter.Scheper@sas.com
License: Apache License 2.0
Platform: UNKNOWN
Requires-Dist: lxml (>=3.4.4,<4.0.0)
Requires-Dist: requests (<3.0.0,>=2.7.0)
